flask_migrate/__init__.py
flask_migrate/cli.py
flask_migrate/templates/aioflask/README
flask_migrate/templates/aioflask/alembic.ini.mako
flask_migrate/templates/aioflask/env.py
flask_migrate/templates/aioflask/script.py.mako
flask_migrate/templates/aioflask-multidb/README
flask_migrate/templates/aioflask-multidb/alembic.ini.mako
flask_migrate/templates/aioflask-multidb/env.py
flask_migrate/templates/aioflask-multidb/script.py.mako
flask_migrate/templates/flask/README
flask_migrate/templates/flask/alembic.ini.mako
flask_migrate/templates/flask/env.py
flask_migrate/templates/flask/script.py.mako
flask_migrate/templates/flask-multidb/README
flask_migrate/templates/flask-multidb/alembic.ini.mako
flask_migrate/templates/flask-multidb/env.py
flask_migrate/templates/flask-multidb/script.py.mako
Flask_Migrate-4.0.7.dist-info/LICENSE
Flask_Migrate-4.0.7.dist-info/METADATA
Flask_Migrate-4.0.7.dist-info/WHEEL
Flask_Migrate-4.0.7.dist-info/top_level.txt
Flask_Migrate-4.0.7.dist-info/RECORD
