Metadata-Version: 2.1
Name: Flask-Migrate
Version: 4.0.7
Summary: SQLAlchemy database migrations for Flask applications using Alembic.
Author-email: Miguel Grinberg <miguel.grinberg@gmail.com>
License: MIT
Project-URL: Homepage, https://github.com/miguelgrinberg/flask-migrate
Project-URL: Bug Tracker, https://github.com/miguelgrinberg/flask-migrate/issues
Classifier: Environment :: Web Environment
Classifier: Intended Audience :: Developers
Classifier: Programming Language :: Python :: 3
Classifier: License :: OSI Approved :: MIT License
Classifier: Operating System :: OS Independent
Requires-Python: >=3.6
License-File: LICENSE
Requires-Dist: Flask>=0.9
Requires-Dist: Flask-SQLAlchemy>=1.0
Requires-Dist: alembic>=1.9.0
